[
  {
    "name": "Source",
    "mode": "NULLABLE",
    "type": "STRING",
    "description": null,
    "fields": []
  },
  {
    "name": "Target",
    "mode": "NULLABLE",
    "type": "STRING",
    "description": null,
    "fields": []
  },
  {
    "name": "Weight",
    "mode": "NULLABLE",
    "type": "FLOAT",
    "description": null,
    "fields": []
  },
  {
    "name": "typeTrans",
    "mode": "NULLABLE",
    "type": "STRING",
    "description": null,
    "fields": []
  },
  {
    "name": "fraud",
    "mode": "NULLABLE",
    "type": "INTEGER",
    "description": null,
    "fields": []
  }
]
